admonitions/__init__.py
admonitions/__metadata__.py
rich_admonitions-0.2.0.dist-info/METADATA
rich_admonitions-0.2.0.dist-info/WHEEL
rich_admonitions-0.2.0.dist-info/licenses/LICENSE
rich_admonitions-0.2.0.dist-info/RECORD
