Metadata-Version: 2.1
Name: rich-admonitions
Version: 0.2.0
Project-URL: Documentation, https://github.com/unknown/rich-admonitions#readme
Project-URL: Issues, https://github.com/unknown/rich-admonitions/issues
Project-URL: Source, https://github.com/unknown/rich-admonitions
Author-email: Joe Carpinelli <jdcarpinelli@gmail.com>
Keywords: admonitions,formatting,rich,terminal
Classifier: Development Status :: 4 - Beta
Classifier: Programming Language :: Python
Classifier: Programming Language :: Python :: 3.8
Classifier: Programming Language :: Python :: 3.9
Classifier: Programming Language :: Python :: 3.10
Classifier: Programming Language :: Python :: Implementation :: CPython
Classifier: Programming Language :: Python :: Implementation :: PyPy
Requires-Python: >=3.8
Requires-Dist: rich
